pyapriltags/__init__.py
pyapriltags/apriltags.py
pyapriltags/libapriltag.so
pyapriltags/py.typed
pyapriltags-3.4.2.1.dist-info/LICENSE.md
pyapriltags-3.4.2.1.dist-info/METADATA
pyapriltags-3.4.2.1.dist-info/WHEEL
pyapriltags-3.4.2.1.dist-info/top_level.txt
pyapriltags-3.4.2.1.dist-info/RECORD
