Metadata-Version: 2.1
Name: pyapriltags
Version: 3.4.2.1
Summary: Python bindings for the Apriltags library
Home-page: https://github.com/WillB97/pyapriltags
Author: Aleksandar Petrov
Author-email: alpetrov@ethz.ch
Maintainer: Will Barber
License: BSD
License-File: LICENSE.md
Requires-Dist: numpy
